kopyt/__init__.py
kopyt/debugger.py
kopyt/exception.py
kopyt/iterator.py
kopyt/lexer.py
kopyt/node.py
kopyt/parser.py
kopyt/position.py
kopyt-0.0.2.dist-info/LICENSE
kopyt-0.0.2.dist-info/METADATA
kopyt-0.0.2.dist-info/WHEEL
kopyt-0.0.2.dist-info/top_level.txt
kopyt-0.0.2.dist-info/RECORD
