Metadata-Version: 2.1
Name: kopyt
Version: 0.0.2
Summary: Kotlin parser in pure Python
Home-page: https://github.com/mvisat/kopyt
Author: Muhamad Visat
Author-email: 9150540+mvisat@users.noreply.github.com
License: UNKNOWN
Project-URL: Bug Tracker, https://github.com/mvisat/kopyt/issues
Platform: UNKNOWN
Classifier: Programming Language :: Python :: 3
Classifier: License :: OSI Approved :: MIT License
Classifier: Operating System :: OS Independent
Classifier: Intended Audience :: Developers
Requires-Python: >=3.7
License-File: LICENSE
